ytmusicdl/__init__.py
ytmusicdl/archive.py
ytmusicdl/cli.py
ytmusicdl/cmdline.py
ytmusicdl/config.py
ytmusicdl/download.py
ytmusicdl/logger.py
ytmusicdl/m3ufile.py
ytmusicdl/metadata.py
ytmusicdl/parsers.py
ytmusicdl/presets.py
ytmusicdl/template.py
ytmusicdl/types.py
ytmusicdl/url.py
ytmusicdl/utils.py
ytmusicdl/ytmusicdl.py
ytmusicdl-2.0b2.dist-info/METADATA
ytmusicdl-2.0b2.dist-info/WHEEL
ytmusicdl-2.0b2.dist-info/entry_points.txt
ytmusicdl-2.0b2.dist-info/licenses/LICENSE
ytmusicdl-2.0b2.dist-info/RECORD
