Metadata-Version: 2.4
Name: YTMusicDL
Version: 2.0b2
Summary: YouTube Music downloader with metadata
Project-URL: Homepage, https://github.com/RaduTek/YTMusicDL
Project-URL: Issues, https://github.com/RaduTek/YTMusicDL/issues
Author-email: RaduTek <me@radutek.uk>
License-File: LICENSE
Classifier: License :: OSI Approved :: MIT License
Classifier: Operating System :: OS Independent
Classifier: Programming Language :: Python :: 3
Requires-Python: >=3.13
Requires-Dist: mutagen>=1.47.0
Requires-Dist: pillow>=11.0.0
Requires-Dist: typeguard>=4.4.4
Requires-Dist: yt-dlp>=2025.6.30
Requires-Dist: ytmusicapi>=1.10.3
